{
  "fio version" : "fio-3.37-2-g07f73",
  "timestamp" : 1744424540,
  "timestamp_ms" : 1744424540924,
  "time" : "Sat Apr 12 02:22:20 2025",
  "global options" : {
    "lat_percentiles" : "1",
    "clat_percentiles" : "0",
    "cpus_allowed_policy" : "shared",
    "ioengine" : "io_uring",
    "rw" : "randwrite",
    "thread" : "1",
    "group_reporting" : "1",
    "percentile_list" : "50:99:99.5:99.9:99.99:99.999",
    "direct" : "1",
    "verify" : "0",
    "runtime" : "7s",
    "filename" : "/dev/nvme0n1"
  },
  "jobs" : [
    {
      "jobname" : "test",
      "groupid" : 0,
      "job_start" : 1744424533788,
      "error" : 0,
      "eta" : 0,
      "elapsed" : 8,
      "job options" : {
        "iodepth" : "1",
        "bs" : "4K",
        "numjobs" : "1",
        "cpus_allowed" : "110",
        "nice" : "0",
        "hipri" : "1"
      },
      "read" : {
        "io_bytes" : 0,
        "io_kbytes" : 0,
        "bw_bytes" : 0,
        "bw" : 0,
        "iops" : 0.000000,
        "runtime" : 0,
        "total_ios" : 0,
        "short_ios" : 0,
        "drop_ios" : 0,
        "slat_ns" : {
          "min" : 0,
          "max" : 0,
          "mean" : 0.000000,
          "stddev" : 0.000000,
          "N" : 0
        },
        "clat_ns" : {
          "min" : 0,
          "max" : 0,
          "mean" : 0.000000,
          "stddev" : 0.000000,
          "N" : 0
        },
        "lat_ns" : {
          "min" : 0,
          "max" : 0,
          "mean" : 0.000000,
          "stddev" : 0.000000,
          "N" : 0
        },
        "bw_min" : 0,
        "bw_max" : 0,
        "bw_agg" : 0.000000,
        "bw_mean" : 0.000000,
        "bw_dev" : 0.000000,
        "bw_samples" : 0,
        "iops_min" : 0,
        "iops_max" : 0,
        "iops_mean" : 0.000000,
        "iops_stddev" : 0.000000,
        "iops_samples" : 0
      },
      "write" : {
        "io_bytes" : 2068357120,
        "io_kbytes" : 2019880,
        "bw_bytes" : 295437383,
        "bw" : 288513,
        "iops" : 72128.267390,
        "runtime" : 7001,
        "total_ios" : 504970,
        "short_ios" : 0,
        "drop_ios" : 0,
        "slat_ns" : {
          "min" : 1379,
          "max" : 410170,
          "mean" : 1771.233329,
          "stddev" : 5679.099101,
          "N" : 504970
        },
        "clat_ns" : {
          "min" : 193,
          "max" : 1846840,
          "mean" : 11673.583165,
          "stddev" : 37988.373759,
          "N" : 504970
        },
        "lat_ns" : {
          "min" : 5288,
          "max" : 1848352,
          "mean" : 13444.816494,
          "stddev" : 39526.207209,
          "N" : 504970,
          "percentile" : {
            "50.000000" : 5472,
            "99.000000" : 211968,
            "99.500000" : 222208,
            "99.900000" : 276480,
            "99.990000" : 473088,
            "99.999000" : 528384
          }
        },
        "bw_min" : 283896,
        "bw_max" : 292232,
        "bw_agg" : 100.000000,
        "bw_mean" : 288554.285714,
        "bw_dev" : 2505.715664,
        "bw_samples" : 14,
        "iops_min" : 70974,
        "iops_max" : 73058,
        "iops_mean" : 72138.571429,
        "iops_stddev" : 626.428916,
        "iops_samples" : 14
      },
      "trim" : {
        "io_bytes" : 0,
        "io_kbytes" : 0,
        "bw_bytes" : 0,
        "bw" : 0,
        "iops" : 0.000000,
        "runtime" : 0,
        "total_ios" : 0,
        "short_ios" : 0,
        "drop_ios" : 0,
        "slat_ns" : {
          "min" : 0,
          "max" : 0,
          "mean" : 0.000000,
          "stddev" : 0.000000,
          "N" : 0
        },
        "clat_ns" : {
          "min" : 0,
          "max" : 0,
          "mean" : 0.000000,
          "stddev" : 0.000000,
          "N" : 0
        },
        "lat_ns" : {
          "min" : 0,
          "max" : 0,
          "mean" : 0.000000,
          "stddev" : 0.000000,
          "N" : 0
        },
        "bw_min" : 0,
        "bw_max" : 0,
        "bw_agg" : 0.000000,
        "bw_mean" : 0.000000,
        "bw_dev" : 0.000000,
        "bw_samples" : 0,
        "iops_min" : 0,
        "iops_max" : 0,
        "iops_mean" : 0.000000,
        "iops_stddev" : 0.000000,
        "iops_samples" : 0
      },
      "sync" : {
        "total_ios" : 0,
        "lat_ns" : {
          "min" : 0,
          "max" : 0,
          "mean" : 0.000000,
          "stddev" : 0.000000,
          "N" : 0
        }
      },
      "job_runtime" : 7000,
      "usr_cpu" : 6.885714,
      "sys_cpu" : 50.342857,
      "ctx" : 185505,
      "majf" : 0,
      "minf" : 6408,
      "iodepth_level" : {
        "1" : 100.000000,
        "2" : 0.000000,
        "4" : 0.000000,
        "8" : 0.000000,
        "16" : 0.000000,
        "32" : 0.000000,
        ">=64" : 0.000000
      },
      "iodepth_submit" : {
        "0" : 0.000000,
        "4" : 100.000000,
        "8" : 0.000000,
        "16" : 0.000000,
        "32" : 0.000000,
        "64" : 0.000000,
        ">=64" : 0.000000
      },
      "iodepth_complete" : {
        "0" : 0.000000,
        "4" : 100.000000,
        "8" : 0.000000,
        "16" : 0.000000,
        "32" : 0.000000,
        "64" : 0.000000,
        ">=64" : 0.000000
      },
      "latency_ns" : {
        "2" : 0.000000,
        "4" : 0.000000,
        "10" : 0.000000,
        "20" : 0.000000,
        "50" : 0.000000,
        "100" : 0.000000,
        "250" : 0.010000,
        "500" : 0.010000,
        "750" : 0.000000,
        "1000" : 0.000000
      },
      "latency_us" : {
        "2" : 0.020199,
        "4" : 33.039388,
        "10" : 62.918193,
        "20" : 0.029507,
        "50" : 0.028913,
        "100" : 0.039606,
        "250" : 3.823197,
        "500" : 0.094659,
        "750" : 0.000000,
        "1000" : 0.000000
      },
      "latency_ms" : {
        "2" : 0.010000,
        "4" : 0.000000,
        "10" : 0.000000,
        "20" : 0.000000,
        "50" : 0.000000,
        "100" : 0.000000,
        "250" : 0.000000,
        "500" : 0.000000,
        "750" : 0.000000,
        "1000" : 0.000000,
        "2000" : 0.000000,
        ">=2000" : 0.000000
      },
      "latency_depth" : 1,
      "latency_target" : 0,
      "latency_percentile" : 100.000000,
      "latency_window" : 0
    },
    {
      "jobname" : "tapp",
      "groupid" : 1,
      "job_start" : 1744424533783,
      "error" : 0,
      "eta" : 0,
      "elapsed" : 8,
      "job options" : {
        "iodepth" : "16",
        "bs" : "64K",
        "numjobs" : "1",
        "cpus_allowed" : "110",
        "nice" : "0"
      },
      "read" : {
        "io_bytes" : 0,
        "io_kbytes" : 0,
        "bw_bytes" : 0,
        "bw" : 0,
        "iops" : 0.000000,
        "runtime" : 0,
        "total_ios" : 0,
        "short_ios" : 0,
        "drop_ios" : 0,
        "slat_ns" : {
          "min" : 0,
          "max" : 0,
          "mean" : 0.000000,
          "stddev" : 0.000000,
          "N" : 0
        },
        "clat_ns" : {
          "min" : 0,
          "max" : 0,
          "mean" : 0.000000,
          "stddev" : 0.000000,
          "N" : 0
        },
        "lat_ns" : {
          "min" : 0,
          "max" : 0,
          "mean" : 0.000000,
          "stddev" : 0.000000,
          "N" : 0
        },
        "bw_min" : 0,
        "bw_max" : 0,
        "bw_agg" : 0.000000,
        "bw_mean" : 0.000000,
        "bw_dev" : 0.000000,
        "bw_samples" : 0,
        "iops_min" : 0,
        "iops_max" : 0,
        "iops_mean" : 0.000000,
        "iops_stddev" : 0.000000,
        "iops_samples" : 0
      },
      "write" : {
        "io_bytes" : 20792672256,
        "io_kbytes" : 20305344,
        "bw_bytes" : 2969957471,
        "bw" : 2900349,
        "iops" : 45317.954578,
        "runtime" : 7001,
        "total_ios" : 317271,
        "short_ios" : 0,
        "drop_ios" : 0,
        "slat_ns" : {
          "min" : 4621,
          "max" : 87407,
          "mean" : 6421.423663,
          "stddev" : 744.054392,
          "N" : 317271
        },
        "clat_ns" : {
          "min" : 94934,
          "max" : 7046316,
          "mean" : 346227.485604,
          "stddev" : 776160.072971,
          "N" : 317271
        },
        "lat_ns" : {
          "min" : 101250,
          "max" : 7052815,
          "mean" : 352648.909267,
          "stddev" : 776119.239126,
          "N" : 317271,
          "percentile" : {
            "50.000000" : 205824,
            "99.000000" : 5079040,
            "99.500000" : 5537792,
            "99.900000" : 6389760,
            "99.990000" : 6914048,
            "99.999000" : 7045120
          }
        },
        "bw_min" : 2884352,
        "bw_max" : 2921856,
        "bw_agg" : 100.000000,
        "bw_mean" : 2900763.428571,
        "bw_dev" : 13223.581254,
        "bw_samples" : 14,
        "iops_min" : 45066,
        "iops_max" : 45654,
        "iops_mean" : 45324.285714,
        "iops_stddev" : 206.809994,
        "iops_samples" : 14
      },
      "trim" : {
        "io_bytes" : 0,
        "io_kbytes" : 0,
        "bw_bytes" : 0,
        "bw" : 0,
        "iops" : 0.000000,
        "runtime" : 0,
        "total_ios" : 0,
        "short_ios" : 0,
        "drop_ios" : 0,
        "slat_ns" : {
          "min" : 0,
          "max" : 0,
          "mean" : 0.000000,
          "stddev" : 0.000000,
          "N" : 0
        },
        "clat_ns" : {
          "min" : 0,
          "max" : 0,
          "mean" : 0.000000,
          "stddev" : 0.000000,
          "N" : 0
        },
        "lat_ns" : {
          "min" : 0,
          "max" : 0,
          "mean" : 0.000000,
          "stddev" : 0.000000,
          "N" : 0
        },
        "bw_min" : 0,
        "bw_max" : 0,
        "bw_agg" : 0.000000,
        "bw_mean" : 0.000000,
        "bw_dev" : 0.000000,
        "bw_samples" : 0,
        "iops_min" : 0,
        "iops_max" : 0,
        "iops_mean" : 0.000000,
        "iops_stddev" : 0.000000,
        "iops_samples" : 0
      },
      "sync" : {
        "total_ios" : 0,
        "lat_ns" : {
          "min" : 0,
          "max" : 0,
          "mean" : 0.000000,
          "stddev" : 0.000000,
          "N" : 0
        }
      },
      "job_runtime" : 7000,
      "usr_cpu" : 13.428571,
      "sys_cpu" : 29.328571,
      "ctx" : 185486,
      "majf" : 0,
      "minf" : 448,
      "iodepth_level" : {
        "1" : 0.100000,
        "2" : 0.100000,
        "4" : 0.100000,
        "8" : 0.100000,
        "16" : 99.995272,
        "32" : 0.000000,
        ">=64" : 0.000000
      },
      "iodepth_submit" : {
        "0" : 0.000000,
        "4" : 100.000000,
        "8" : 0.000000,
        "16" : 0.000000,
        "32" : 0.000000,
        "64" : 0.000000,
        ">=64" : 0.000000
      },
      "iodepth_complete" : {
        "0" : 0.000000,
        "4" : 99.999685,
        "8" : 0.000000,
        "16" : 0.100000,
        "32" : 0.000000,
        "64" : 0.000000,
        ">=64" : 0.000000
      },
      "latency_ns" : {
        "2" : 0.000000,
        "4" : 0.000000,
        "10" : 0.000000,
        "20" : 0.000000,
        "50" : 0.000000,
        "100" : 0.000000,
        "250" : 0.000000,
        "500" : 0.000000,
        "750" : 0.000000,
        "1000" : 0.000000
      },
      "latency_us" : {
        "2" : 0.000000,
        "4" : 0.000000,
        "10" : 0.000000,
        "20" : 0.000000,
        "50" : 0.000000,
        "100" : 0.151921,
        "250" : 95.643157,
        "500" : 0.019857,
        "750" : 0.019226,
        "1000" : 0.043811
      },
      "latency_ms" : {
        "2" : 0.577109,
        "4" : 1.612817,
        "10" : 1.932102,
        "20" : 0.000000,
        "50" : 0.000000,
        "100" : 0.000000,
        "250" : 0.000000,
        "500" : 0.000000,
        "750" : 0.000000,
        "1000" : 0.000000,
        "2000" : 0.000000,
        ">=2000" : 0.000000
      },
      "latency_depth" : 16,
      "latency_target" : 0,
      "latency_percentile" : 100.000000,
      "latency_window" : 0
    }
  ],
  "disk_util" : [
    {
      "name" : "nvme0n1",
      "read_ios" : 49,
      "write_ios" : 808581,
      "read_sectors" : 2120,
      "write_sectors" : 43952568,
      "read_merges" : 0,
      "write_merges" : 0,
      "read_ticks" : 0,
      "write_ticks" : 66178,
      "in_queue" : 66178,
      "util" : 82.790166
    }
  ]
}
